chain_of_thought/__init__.py
chain_of_thought/cot_manager.py
chain_of_thought/llm_interface.py
chain_of_thought/utils.py
pocketgroq/__init__.py
pocketgroq/autonomous_agent.py
pocketgroq/config.py
pocketgroq/enhanced_web_tool.py
pocketgroq/exceptions.py
pocketgroq/groq_provider.py
pocketgroq/rag_manager.py
pocketgroq/utils.py
pocketgroq/web_tool.py
pocketgroq/chain_of_thought/__init__.py
pocketgroq/chain_of_thought/cot_manager.py
pocketgroq/chain_of_thought/llm_interface.py
pocketgroq/chain_of_thought/utils.py
pocketgroq-0.5.6.dist-info/METADATA
pocketgroq-0.5.6.dist-info/WHEEL
pocketgroq-0.5.6.dist-info/top_level.txt
pocketgroq-0.5.6.dist-info/RECORD
