Metadata-Version: 2.1
Name: pocketgroq
Version: 0.5.6
Summary: A library for easy integration with Groq API, including web scraping, image handling, and Chain of Thought reasoning
Home-page: https://github.com/jgravelle/pocketgroq
Author: PocketGroq Team
Author-email: j@gravelle.us
Project-URL: Bug Tracker, https://github.com/jgravelle/pocketgroq/issues
Classifier: Development Status :: 3 - Alpha
Classifier: Intended Audience :: Developers
Classifier: License :: OSI Approved :: MIT License
Classifier: Operating System :: OS Independent
Classifier: Programming Language :: Python :: 3
Classifier: Programming Language :: Python :: 3.7
Classifier: Programming Language :: Python :: 3.8
Classifier: Programming Language :: Python :: 3.9
Classifier: Programming Language :: Python :: 3.10
Classifier: Programming Language :: Python :: 3.11
Classifier: Programming Language :: Python :: 3.12
Requires-Python: >=3.7
Requires-Dist: bs4 >=0.0.2
Requires-Dist: groq >=0.8.0
Requires-Dist: python-dotenv >=0.19.1
Requires-Dist: pytest >=7.3.1
Requires-Dist: pytest-asyncio >=0.21.0
Requires-Dist: requests >=2.32.3
Requires-Dist: langchain >=0.3.1
Requires-Dist: langchain-groq >=0.2.0
Requires-Dist: langchain-community >=0.3.1
Requires-Dist: markdown2 >=2.5.0
Requires-Dist: faiss-cpu >=1.8.0.post1
Requires-Dist: ollama >=0.3.3
Requires-Dist: html2text >=2024.2.26
Provides-Extra: dev
Requires-Dist: pytest >=7.3.1 ; extra == 'dev'
Requires-Dist: pytest-asyncio >=0.21.0 ; extra == 'dev'
